Tailer/LocalAligner.py
Tailer/Tailer.py
Tailer/TailerFunctions.py
Tailer/__init__.py
Tailer/miRNA_tailer.py
jla_tailer-0.1.18.dist-info/LICENSE
jla_tailer-0.1.18.dist-info/METADATA
jla_tailer-0.1.18.dist-info/WHEEL
jla_tailer-0.1.18.dist-info/entry_points.txt
jla_tailer-0.1.18.dist-info/top_level.txt
jla_tailer-0.1.18.dist-info/RECORD
