Metadata-Version: 2.1
Name: jla-tailer
Version: 0.1.18
Summary: Tool to find 3' tailing of non-coding RNAs
Home-page: https://github.com/TimNicholsonShaw/tailer
Author: Tim Nicholson-Shaw
Author-email: timnicholsonshaw@gmail.com
License: UNKNOWN
Project-URL: Lab Website, https://labs.biology.ucsd.edu/lykkeandersen/index.html
Keywords: Sequencing,ncRNAs,Bioinformatics
Platform: UNKNOWN
Classifier: Development Status :: 3 - Alpha
Classifier: License :: OSI Approved :: MIT License
Classifier: Programming Language :: Python :: 3 :: Only
Requires-Python: >=3.6
License-File: LICENSE
Requires-Dist: pysam
Requires-Dist: Bio
Requires-Dist: gffutils
Requires-Dist: tqdm
Requires-Dist: requests
